contracts/wake/Create3.sol
contracts/wake/Create3Deployer.sol
contracts/wake/ERC1967Factory.sol
contracts/wake/console.sol
contracts/wake/interfaces/IERC1155.sol
contracts/wake/interfaces/IERC165.sol
contracts/wake/interfaces/IERC20.sol
contracts/wake/interfaces/IERC20Metadata.sol
contracts/wake/interfaces/IERC721.sol
examples/.gitignore
examples/counter/README.md
examples/counter/contracts/Counter.sol
examples/counter/contracts/Gateway.sol
examples/counter/contracts/Imports.sol
examples/counter/hardhat.config.js
examples/counter/package-lock.json
examples/counter/package.json
examples/counter/scripts/__init__.py
examples/counter/scripts/deploy.py
examples/counter/tests/__init__.py
examples/counter/tests/test_counter.py
examples/counter/tests/test_counter_fuzz.py
examples/counter/tests/test_counter_fuzz_failing.py
examples/counter/tests/test_crosschain.py
examples/counter/wake.toml
wake/__init__.py
wake/analysis/__init__.py
wake/analysis/cfg.py
wake/analysis/expressions.py
wake/analysis/graph.py
wake/analysis/interface.py
wake/analysis/modifies_state.py
wake/analysis/ownable.py
wake/analysis/proxy.py
wake/analysis/utils.py
wake/cli/__init__.py
wake/cli/__main__.py
wake/cli/accounts.py
wake/cli/compile.py
wake/cli/console.py
wake/cli/detect.py
wake/cli/init.py
wake/cli/lsp.py
wake/cli/open.py
wake/cli/param_types.py
wake/cli/print.py
wake/cli/run.py
wake/cli/svm.py
wake/cli/test.py
wake/compiler/__init__.py
wake/compiler/build_data_model.py
wake/compiler/compilation_unit.py
wake/compiler/compiler.py
wake/compiler/exceptions.py
wake/compiler/solc_frontend/__init__.py
wake/compiler/solc_frontend/exceptions.py
wake/compiler/solc_frontend/input_data_model.py
wake/compiler/solc_frontend/output_data_model.py
wake/compiler/solc_frontend/solc_runner.py
wake/compiler/source_path_resolver.py
wake/compiler/source_unit_name_resolver.py
wake/config/__init__.py
wake/config/data_model.py
wake/config/wake_config.py
wake/core/__init__.py
wake/core/enums.py
wake/core/exceptions.py
eth_wake-4.20.1.dist-info/LICENSE
eth_wake-4.20.1.dist-info/METADATA
eth_wake-4.20.1.dist-info/WHEEL
eth_wake-4.20.1.dist-info/entry_points.txt
eth_wake-4.20.1.dist-info/RECORD
