Metadata-Version: 2.3
Name: eth-wake
Version: 4.20.1
Summary: Wake is a Python-based Solidity development and testing framework with built-in vulnerability detectors.
License: ISC
Keywords: ethereum,solidity,security,testing,development,static analysis,framework,audit
Author: Ackee Blockchain
Requires-Python: >=3.8,<4.0
Classifier: License :: OSI Approved
Classifier: Programming Language :: Python :: 3
Classifier: Programming Language :: Python :: 3.8
Classifier: Programming Language :: Python :: 3.9
Classifier: Programming Language :: Python :: 3.10
Classifier: Programming Language :: Python :: 3.11
Classifier: Programming Language :: Python :: 3.12
Classifier: Programming Language :: Python :: 3.13
Provides-Extra: dev
Provides-Extra: tests
Requires-Dist: GitPython (>=3.1.20,<4.0.0) ; extra == "tests"
Requires-Dist: abch_tree_sitter (>=1.1.2,<2.0.0)
Requires-Dist: abch_tree_sitter_solidity (>=1.3.0,<2.0.0)
Requires-Dist: aiofiles (>=0.8,<0.9)
Requires-Dist: aiohttp (>=3.8,<4.0) ; python_version < "3.12"
Requires-Dist: aiohttp (>=3.9.0b1) ; python_version >= "3.12"
Requires-Dist: black (>=22,<23) ; extra == "dev"
Requires-Dist: cairosvg (>=2.7,<3.0) ; extra == "dev"
Requires-Dist: certifi (>=2024.2.2) ; sys_platform == "darwin"
Requires-Dist: click (>=8,<9)
Requires-Dist: eth-abi (>=4.0.0b2,<5.0.0)
Requires-Dist: eth-account (>=0.8,<0.9)
Requires-Dist: eth-utils (>=2.1,<3.0)
Requires-Dist: graphviz (>=0.19,<0.20)
Requires-Dist: importlib-metadata (>=4.13,<5.0) ; python_version < "3.10"
Requires-Dist: intervaltree (>=3.1,<4.0)
Requires-Dist: ipdb (>=0.13.9,<0.14.0)
Requires-Dist: isort (>=5,<6) ; extra == "dev"
Requires-Dist: jschema-to-python (>=1.2.3,<2.0.0)
Requires-Dist: lazy-import (>=0.2.2,<0.3.0)
Requires-Dist: mike (>=2.0.0,<3.0.0) ; extra == "dev"
Requires-Dist: mkdocs-material (>=9.5.17,<10.0.0) ; extra == "dev"
Requires-Dist: mkdocstrings (>=0.26,<0.27) ; extra == "dev"
Requires-Dist: mkdocstrings-python (>=1.11,<2.0) ; extra == "dev"
Requires-Dist: networkx (>=2.5,<3.0)
Requires-Dist: packaging (>=22.0)
Requires-Dist: parsimonious (>=0.9,<0.10)
Requires-Dist: pathvalidate (>=2.5,<3.0)
Requires-Dist: pillow (>=10.1,<11.0) ; (python_version >= "3.12") and (extra == "dev")
Requires-Dist: pillow (>=9,<10) ; (python_version < "3.12") and (extra == "dev")
Requires-Dist: pycryptodome (>=3.19.0)
Requires-Dist: pydantic (>=2.7,<3.0)
Requires-Dist: pygments (>=2,<3) ; extra == "dev"
Requires-Dist: pymdown-extensions (>=10,<11) ; extra == "dev"
Requires-Dist: pytest (>=7,<8)
Requires-Dist: pytest-asyncio (>=0.17,<0.18) ; extra == "tests"
Requires-Dist: pywin32 (>=302) ; sys_platform == "win32"
Requires-Dist: rich (>=13.3.2,<14.0.0)
Requires-Dist: rich-click (>=1.7.1,<2.0.0)
Requires-Dist: sarif-om (>=1.0.4,<2.0.0)
Requires-Dist: tblib (>=1.7,<2.0)
Requires-Dist: tomli (>=2,<3)
Requires-Dist: tomli-w (>=1.0.0,<2.0.0)
Requires-Dist: typing-extensions (>=4.12)
Requires-Dist: watchdog (>=4,<5)
Requires-Dist: websocket-client (>=1.4,<2.0)
Project-URL: Documentation, https://ackee.xyz/wake/docs/latest
Project-URL: Homepage, https://getwake.io
Project-URL: Repository, https://github.com/Ackee-Blockchain/wake
Project-URL: VS Code Extension, https://marketplace.visualstudio.com/items?itemName=AckeeBlockchain.tools-for-solidity
